onetl/VERSION
onetl/__init__.py
onetl/exception.py
onetl/log.py
onetl/version.py
onetl/_metrics/__init__.py
onetl/_metrics/command.py
onetl/_metrics/driver.py
onetl/_metrics/executor.py
onetl/_metrics/extract.py
onetl/_metrics/input.py
onetl/_metrics/output.py
onetl/_metrics/recorder.py
onetl/_metrics/listener/__init__.py
onetl/_metrics/listener/base.py
onetl/_metrics/listener/execution.py
onetl/_metrics/listener/job.py
onetl/_metrics/listener/listener.py
onetl/_metrics/listener/stage.py
onetl/_metrics/listener/task.py
onetl/_util/__init__.py
onetl/_util/alias.py
onetl/_util/classproperty.py
onetl/_util/file.py
onetl/_util/hadoop.py
onetl/_util/java.py
onetl/_util/scala.py
onetl/_util/spark.py
onetl/_util/sql.py
onetl/_util/version.py
onetl/base/__init__.py
onetl/base/base_connection.py
onetl/base/base_db_connection.py
onetl/base/base_file_connection.py
onetl/base/base_file_df_connection.py
onetl/base/base_file_filter.py
onetl/base/base_file_format.py
onetl/base/base_file_limit.py
onetl/base/contains_exception.py
onetl/base/contains_get_df_schema.py
onetl/base/contains_get_min_max_values.py
onetl/base/path_protocol.py
onetl/base/path_stat_protocol.py
onetl/base/pure_path_protocol.py
onetl/base/supports_rename_dir.py
onetl/connection/__init__.py
onetl/connection/kerberos_helpers.py
onetl/connection/db_connection/__init__.py
onetl/connection/db_connection/clickhouse/__init__.py
onetl/connection/db_connection/clickhouse/connection.py
onetl/connection/db_connection/clickhouse/dialect.py
onetl/connection/db_connection/clickhouse/options.py
onetl/connection/db_connection/db_connection/__init__.py
onetl/connection/db_connection/db_connection/connection.py
onetl/connection/db_connection/db_connection/dialect.py
onetl/connection/db_connection/dialect_mixins/__init__.py
onetl/connection/db_connection/dialect_mixins/not_support_columns.py
onetl/connection/db_connection/dialect_mixins/not_support_df_schema.py
onetl/connection/db_connection/dialect_mixins/not_support_hint.py
onetl-0.15.0.dist-info/licenses/LICENSE.txt
onetl-0.15.0.dist-info/METADATA
onetl-0.15.0.dist-info/WHEEL
onetl-0.15.0.dist-info/entry_points.txt
onetl-0.15.0.dist-info/top_level.txt
onetl-0.15.0.dist-info/RECORD
