Metadata-Version: 2.4
Name: onetl
Version: 0.15.0
Summary: One ETL tool to rule them all
Home-page: https://github.com/MobileTeleSystems/onetl
Author: MWS Data Bridge
Author-email: onetools@mts.ru
License: Apache-2.0
Project-URL: Documentation, https://onetl.readthedocs.io/
Project-URL: Source, https://github.com/MobileTeleSystems/onetl
Project-URL: CI/CD, https://github.com/MobileTeleSystems/onetl/actions
Project-URL: Tracker, https://github.com/MobileTeleSystems/onetl/issues
Keywords: Spark,ETL,JDBC,HWM
Classifier: Development Status :: 4 - Beta
Classifier: Framework :: Pydantic
Classifier: Framework :: Pydantic :: 1
Classifier: Framework :: Pydantic :: 2
Classifier: Intended Audience :: Developers
Classifier: License :: OSI Approved :: Apache Software License
Classifier: Operating System :: OS Independent
Classifier: Programming Language :: Python :: 3 :: Only
Classifier: Programming Language :: Python :: 3.7
Classifier: Programming Language :: Python :: 3.8
Classifier: Programming Language :: Python :: 3.8
Classifier: Programming Language :: Python :: 3.9
Classifier: Programming Language :: Python :: 3.10
Classifier: Programming Language :: Python :: 3.11
Classifier: Programming Language :: Python :: 3.12
Classifier: Programming Language :: Python :: 3.13
Classifier: Topic :: Software Development :: Libraries
Classifier: Topic :: Software Development :: Libraries :: Java Libraries
Classifier: Topic :: Software Development :: Libraries :: Python Modules
Classifier: Topic :: System :: Distributed Computing
Classifier: Typing :: Typed
Requires-Python: >=3.7
License-File: LICENSE.txt
Requires-Dist: etl-entities<2.7,>=2.5
Requires-Dist: evacuator<1.1,>=1.0
Requires-Dist: frozendict
Requires-Dist: humanize
Requires-Dist: importlib_metadata>=3.6.0
Requires-Dist: ordered-set
Requires-Dist: platformdirs
Requires-Dist: pydantic!=1.10.2,<3,>=1.9.2
Requires-Dist: pyyaml
Requires-Dist: typing_extensions!=4.6.1,>=4.5.0; python_version == "3.7"
Requires-Dist: typing_extensions>=4.5.0; python_version > "3.7"
Provides-Extra: spark
Requires-Dist: pyspark; extra == "spark"
Provides-Extra: ftp
Requires-Dist: ftputil>=5.0.4; extra == "ftp"
Provides-Extra: ftps
Requires-Dist: ftputil>=5.0.4; extra == "ftps"
Provides-Extra: sftp
Requires-Dist: paramiko; extra == "sftp"
Provides-Extra: samba
Requires-Dist: pysmb; extra == "samba"
Provides-Extra: hdfs
Requires-Dist: hdfs>2; extra == "hdfs"
Provides-Extra: s3
Requires-Dist: minio<8; extra == "s3"
Provides-Extra: webdav
Requires-Dist: webdavclient3; extra == "webdav"
Provides-Extra: files
Requires-Dist: ftputil>=5.0.4; extra == "files"
Requires-Dist: paramiko; extra == "files"
Requires-Dist: hdfs>2; extra == "files"
Requires-Dist: minio<8; extra == "files"
Requires-Dist: webdavclient3; extra == "files"
Requires-Dist: pysmb; extra == "files"
Provides-Extra: kerberos
Requires-Dist: requests-kerberos>=0.7.0; extra == "kerberos"
Provides-Extra: all
Requires-Dist: ftputil>=5.0.4; extra == "all"
Requires-Dist: paramiko; extra == "all"
Requires-Dist: hdfs>2; extra == "all"
Requires-Dist: minio<8; extra == "all"
Requires-Dist: webdavclient3; extra == "all"
Requires-Dist: pysmb; extra == "all"
Requires-Dist: requests-kerberos>=0.7.0; extra == "all"
Requires-Dist: pyspark; extra == "all"
Dynamic: author
Dynamic: author-email
Dynamic: classifier
Dynamic: description
Dynamic: description-content-type
Dynamic: home-page
Dynamic: keywords
Dynamic: license
Dynamic: license-file
Dynamic: project-url
Dynamic: provides-extra
Dynamic: requires-dist
Dynamic: requires-python
Dynamic: summary
